setup.py
gnnlens/__init__.py
gnnlens/api.py
gnnlens/constants.py
gnnlens/db.py
gnnlens/libinfo.py
gnnlens/server.py
gnnlens/vis.py
gnnlens/writer.py
gnnlens.egg-info/PKG-INFO
gnnlens.egg-info/SOURCES.txt
gnnlens.egg-info/dependency_links.txt
gnnlens.egg-info/entry_points.txt
gnnlens.egg-info/not-zip-safe
gnnlens.egg-info/requires.txt
gnnlens.egg-info/top_level.txt
gnnlens/visbuild/asset-manifest.json
gnnlens/visbuild/datagen.py
gnnlens/visbuild/eweights-2.txt
gnnlens/visbuild/eweights.txt
gnnlens/visbuild/index.html
gnnlens/visbuild/manifest.json
gnnlens/visbuild/out.txt
gnnlens/visbuild/precache-manifest.3a7ce0b24b434c72ea8841a90af31981.js
gnnlens/visbuild/precache-manifest.61eeda3f5dd1495de4355615963b0c0f.js
gnnlens/visbuild/robots.txt
gnnlens/visbuild/service-worker.js
gnnlens/visbuild/static/css/2.929389fa.chunk.css
gnnlens/visbuild/static/css/2.929389fa.chunk.css.map
gnnlens/visbuild/static/css/main.8d5084fd.chunk.css
gnnlens/visbuild/static/css/main.8d5084fd.chunk.css.map
gnnlens/visbuild/static/js/2.b9f0e663.chunk.js
gnnlens/visbuild/static/js/2.b9f0e663.chunk.js.LICENSE.txt
gnnlens/visbuild/static/js/2.b9f0e663.chunk.js.map
gnnlens/visbuild/static/js/main.0f983eeb.chunk.js
gnnlens/visbuild/static/js/main.0f983eeb.chunk.js.map
gnnlens/visbuild/static/js/main.e553e190.chunk.js
gnnlens/visbuild/static/js/main.e553e190.chunk.js.map
gnnlens/visbuild/static/js/runtime-main.ce081a3c.js
gnnlens/visbuild/static/js/runtime-main.ce081a3c.js.map
gnnlens/visbuild/static/media/logo2.4b8ec5cf.png